predictor/__init__.py
predictor/main.py
predictor/common/__init__.py
predictor/common/constants.py
predictor/converter/__init__.py
predictor/converter/intraday_dto_converter.py
predictor/dto/__init__.py
predictor/dto/intraday_dto.py
predictor/dto/prediction_dto.py
predictor/exception/__init__.py
predictor/exception/predictor_exception.py
predictor/utils/__init__.py
predictor/utils/intraday_utils.py
predictor/utils/predictor_utils.py
predictor/utils/utils.py
trading_bot_predictor-0.0.1.dist-info/LICENSE
trading_bot_predictor-0.0.1.dist-info/METADATA
trading_bot_predictor-0.0.1.dist-info/WHEEL
trading_bot_predictor-0.0.1.dist-info/top_level.txt
trading_bot_predictor-0.0.1.dist-info/RECORD
