Metadata-Version: 2.1
Name: trading-bot-predictor
Version: 0.0.1
Summary: Timeseries forecasting for stock prediction
Home-page: https://github.com/Asconius/predictor
Author: asconius
License: UNKNOWN
Platform: UNKNOWN
Classifier: Programming Language :: Python :: 3
Classifier: License :: OSI Approved :: Apache Software License
Classifier: Operating System :: OS Independent
Requires-Python: >=3.6
